setup.py
xlwt/BIFFRecords.py
xlwt/Bitmap.py
xlwt/Cell.py
xlwt/Column.py
xlwt/CompoundDoc.py
xlwt/ExcelFormula.py
xlwt/ExcelFormulaLexer.py
xlwt/ExcelFormulaParser.py
xlwt/ExcelMagic.py
xlwt/Formatting.py
xlwt/Row.py
xlwt/Style.py
xlwt/UnicodeUtils.py
xlwt/Utils.py
xlwt/Workbook.py
xlwt/Worksheet.py
xlwt/__init__.py
xlwt/antlr.py
xlwt/doc/pattern_examples.xls
xlwt/doc/xlwt.html
xlwt/examples/big-16Mb.py
xlwt/examples/big-16Mb.xls
xlwt/examples/big-35Mb.py
xlwt/examples/blanks.py
xlwt/examples/blanks.xls
xlwt/examples/col_width.py
xlwt/examples/col_width.xls
xlwt/examples/country.py
xlwt/examples/country.xls
xlwt/examples/dates.py
xlwt/examples/dates.xls
xlwt/examples/example.xls
xlwt/examples/format.py
xlwt/examples/format.xls
xlwt/examples/formula_names.py
xlwt/examples/formulas.py
xlwt/examples/formulas.xls
xlwt/examples/hyperlinks.py
xlwt/examples/hyperlinks.xls
xlwt/examples/image.py
xlwt/examples/image_chg_col_wid.py
xlwt/examples/image_chg_col_wid.xls
xlwt/examples/merged.py
xlwt/examples/merged.xls
xlwt/examples/merged0.py
xlwt/examples/merged0.xls
xlwt/examples/merged1.py
xlwt/examples/merged1.xls
xlwt/examples/mini.py
xlwt/examples/mini.xls
xlwt/examples/num_formats.py
xlwt/examples/num_formats.xls
xlwt/examples/numbers.xls
xlwt/examples/numbers_demo.py
xlwt/examples/outline.py
xlwt/examples/panes.py
xlwt/examples/panes.xls
xlwt/examples/panes2.py
xlwt/examples/panes2.xls
xlwt/examples/panes3.py
xlwt/examples/panes3.xls
xlwt/examples/parse-fmla.py
xlwt/examples/protection.py
xlwt/examples/protection.xls
xlwt/examples/python.bmp
xlwt/examples/row_styles.py
xlwt/examples/row_styles.xls
xlwt/examples/row_styles_empty.py
xlwt/examples/simple.py
xlwt/examples/sst.py
xlwt/examples/sst.xls
xlwt/examples/unicode0.py
xlwt/examples/unicode0.xls
xlwt/examples/unicode1.py
xlwt/examples/unicode1.xls
xlwt/examples/unicode2.py
xlwt/examples/unicode2.xls
xlwt/examples/wsprops.py
xlwt/examples/xlwt_easyxf_simple_demo.py
xlwt/examples/xlwt_easyxf_simple_demo.xls
xlwt_future.egg-info/PKG-INFO
xlwt_future.egg-info/SOURCES.txt
xlwt_future.egg-info/dependency_links.txt
xlwt_future.egg-info/requires.txt
xlwt_future.egg-info/top_level.txt